nn_tilde/__init__.py
nn_tilde/buffer.py
nn_tilde/codegen.py
nn_tilde/module.py
nn_tilde/templates/__init__.py
nn_tilde/templates/attributes.py
nn_tilde/templates/buffers.py
nn_tilde-1.6.0.dist-info/licenses/LICENSE
nn_tilde-1.6.0.dist-info/METADATA
nn_tilde-1.6.0.dist-info/WHEEL
nn_tilde-1.6.0.dist-info/top_level.txt
nn_tilde-1.6.0.dist-info/RECORD
