Metadata-Version: 2.4
Name: nn_tilde
Version: 1.6.0
Summary: Set of tools to create nn_tilde compatible models.
Author: Antoine CAILLON & Axel CHEMLA--ROMEU-SANTOS
Author-email: chemla@ircam.fr
Classifier: Programming Language :: Python :: 3
Classifier: License :: OSI Approved :: MIT License
Classifier: Operating System :: OS Independent
Requires-Python: >=3.11
License-File: LICENSE
Requires-Dist: torch==2.5
Requires-Dist: cached_conv>=2.5.0
Dynamic: author
Dynamic: author-email
Dynamic: classifier
Dynamic: description
Dynamic: description-content-type
Dynamic: license-file
Dynamic: requires-dist
Dynamic: requires-python
Dynamic: summary
